salimness/__init__.py
salimness/__main__.py
salimness/example.py
salimness/py.typed
salimness-0.1.0.dist-info/entry_points.txt
salimness-0.1.0.dist-info/LICENSE
salimness-0.1.0.dist-info/WHEEL
salimness-0.1.0.dist-info/METADATA
salimness-0.1.0.dist-info/RECORD
