Metadata-Version: 2.1
Name: salimness
Version: 0.1.0
Summary: A karma-based measurement to gauge salimness in your social footprint
Home-page: https://github.com/nimmanarati/salimness
License: MIT
Author: nimmanarati
Author-email: nimmanarati@protonmail.com
Requires-Python: >=3.7,<4.0
Classifier: Development Status :: 3 - Alpha
Classifier: Intended Audience :: Developers
Classifier: License :: OSI Approved :: MIT License
Classifier: Operating System :: OS Independent
Classifier: Programming Language :: Python :: 3
Classifier: Programming Language :: Python :: 3.7
Classifier: Programming Language :: Python :: 3.8
Classifier: Programming Language :: Python :: 3.9
Classifier: Topic :: Software Development :: Libraries :: Python Modules
Requires-Dist: importlib_metadata (>=1.6.0,<2.0.0); python_version < "3.8"
Requires-Dist: rich (>=8.0.0,<9.0.0)
Requires-Dist: typer[all] (>=0.3.2,<0.4.0)
Project-URL: Repository, https://github.com/nimmanarati/salimness
